logging_nice_handlers/__init__.py
logging_nice_handlers/all_level_file_handler.py
logging_nice_handlers/filters.py
logging_nice_handlers/jupyter_stream_handler.py
logging_nice_handlers-0.1.0.dist-info/AUTHORS.rst
logging_nice_handlers-0.1.0.dist-info/LICENSE.txt
logging_nice_handlers-0.1.0.dist-info/METADATA
logging_nice_handlers-0.1.0.dist-info/WHEEL
logging_nice_handlers-0.1.0.dist-info/top_level.txt
logging_nice_handlers-0.1.0.dist-info/RECORD
